{"version":1,"functions":{"/new-script":{},"/authorize/[token]":{},"/":{},"/script/[scriptId]/new-diagnosis":{},"/login":{},"/script/[scriptId]":{},"/script/[scriptId]/screen/[screenId]":{},"/data-keys/edit/[dataKeyId]":{},"/script/[scriptId]/new-screen":{},"/configuration":{},"/script/[scriptId]/diagnosis/[diagnosisId]":{},"/data-keys":{},"/changelogs":{},"/drugs-fluids-and-feeds":{},"/hospitals":{},"/settings/data":{},"/sessions":{},"/sessions/[sessionId]":{},"/account":{},"/settings/logs":{},"/settings":{},"/data-keys/new":{},"/settings/sys":{},"/settings/app":{},"/users":{},"/diagnoses":{},"/drugs-fluids-and-feeds/[itemId]/metadata":{},"/users/edit/[uuid]":{},"/users/add":{},"/drugs-fluids-and-feeds/metadata":{},"/screens":{},"/scripts/[scriptId]/metadata":{}}}