{"version":1,"functions":{"/authorize/[token]":{},"/new-script":{},"/login":{},"/script/[scriptId]/new-problem":{},"/script/[scriptId]/diagnosis/[diagnosisId]":{},"/script/[scriptId]/problem/[problemId]":{},"/script/[scriptId]/new-screen":{},"/script/[scriptId]/screen/[screenId]":{},"/script/[scriptId]":{},"/script/[scriptId]/new-diagnosis":{},"/account":{},"/":{},"/configuration":{},"/changelogs":{},"/data-keys/edit/[dataKeyId]":{},"/data-keys/[dataKeyId]/metadata":{},"/data-keys/metadata":{},"/data-keys":{},"/hospitals":{},"/drugs-fluids-and-feeds":{},"/sessions":{},"/settings":{},"/settings/sys":{},"/settings/logs":{},"/settings/app":{},"/sessions/[sessionId]":{},"/settings/data":{},"/users/edit/[uuid]":{},"/data-keys/new":{},"/diagnoses":{},"/drugs-fluids-and-feeds/[itemId]/metadata":{},"/screens":{},"/scripts/[scriptId]/metadata":{},"/drugs-fluids-and-feeds/metadata":{},"/users":{},"/users/add":{}}}