{
  "version": 3,
  "middleware": {
    "/": {
      "files": [
        "prerender-manifest.js",
        "server/edge-runtime-webpack.js",
        "server/middleware.js"
      ],
      "name": "middleware",
      "page": "/",
      "matchers": [
        {
          "regexp": "^/.*$",
          "originalSource": "/:path*"
        }
      ],
      "wasm": [],
      "assets": [],
      "environments": {
        "previewModeId": "562403755aaf49c0358db020cdc5e362",
        "previewModeSigningKey": "510225c9ac7064e26dec3b0dfbd9ede30ff5ee9dd1721f4fb5934f56e7aaf8c2",
        "previewModeEncryptionKey": "c8926905a309707aac0bd3d21949b88365c98d6b68b39b78966bccd524ebdac9"
      }
    }
  },
  "functions": {},
  "sortedMiddleware": [
    "/"
  ]
}