{
  "version": 3,
  "middleware": {
    "/": {
      "files": [
        "prerender-manifest.js",
        "server/edge-runtime-webpack.js",
        "server/middleware.js"
      ],
      "name": "middleware",
      "page": "/",
      "matchers": [
        {
          "regexp": "^/.*$",
          "originalSource": "/:path*"
        }
      ],
      "wasm": [],
      "assets": [],
      "environments": {
        "previewModeId": "26e54621f367d5407936a7568a214734",
        "previewModeSigningKey": "41d71c654bb0d8616e02aae512c3673a2a5d5a42687ad81d106cbf4333503ea7",
        "previewModeEncryptionKey": "301cc2d4ae97df9d0a523e0558a84fe52bcc23a7ed35864af41dcc682029c0bf"
      }
    }
  },
  "functions": {},
  "sortedMiddleware": [
    "/"
  ]
}